{
  "chapterTopics": {
    "1": [
      {
        "outline": "Paul’s Greeting to the Ephesians",
        "verses": [
          "1-2"
        ],
        "references": [
          "Acts 19:8–12",
          "Revelation 2:1–7"
        ]
      },
      {
        "outline": "Spiritual Blessings",
        "verses": [
          "3-14"
        ],
        "references": [
          "Romans 8:28–34"
        ]
      },
      {
        "outline": "Spiritual Wisdom",
        "verses": [
          "15-23"
        ],
        "references": [
          "1 Corinthians 2:6–16"
        ]
      }
    ],
    "2": [
      {
        "outline": "Alive with Christ",
        "verses": [
          "1-10"
        ],
        "references": [
          "Colossians 2:6–23"
        ]
      },
      {
        "outline": "One in Christ",
        "verses": [
          "11-18"
        ],
        "references": [
          "Philippians 2:1–4"
        ]
      },
      {
        "outline": "Christ Our Cornerstone",
        "verses": [
          "19-22"
        ],
        "references": [
          "Isaiah 28:14–22",
          "1 Corinthians 3:10–15",
          "1 Peter 2:1–8"
        ]
      }
    ],
    "3": [
      {
        "outline": "The Mystery of the Gospel",
        "verses": [
          "1-13"
        ],
        "references": []
      },
      {
        "outline": "Paul’s Prayer for the Ephesians",
        "verses": [
          "14-21"
        ],
        "references": []
      }
    ],
    "4": [
      {
        "outline": "Unity in the Body",
        "verses": [
          "1-16"
        ],
        "references": [
          "Psalms 133:1–3",
          "1 Corinthians 1:10–17"
        ]
      },
      {
        "outline": "New Life in Christ",
        "verses": [
          "17-32"
        ],
        "references": [
          "Colossians 3:1–17"
        ]
      }
    ],
    "5": [
      {
        "outline": "Imitators of God",
        "verses": [
          "1-7"
        ],
        "references": []
      },
      {
        "outline": "Children of Light",
        "verses": [
          "8-20"
        ],
        "references": []
      },
      {
        "outline": "Wives and Husbands",
        "verses": [
          "21-33"
        ],
        "references": [
          "Song 1:1–17",
          "1 Peter 3:1–7"
        ]
      }
    ],
    "6": [
      {
        "outline": "Children and Parents",
        "verses": [
          "1-4"
        ],
        "references": [
          "Colossians 3:18–21"
        ]
      },
      {
        "outline": "Serving with Honor",
        "verses": [
          "5-9"
        ],
        "references": [
          "Colossians 3:22–25",
          "1 Timothy 6:1–2"
        ]
      },
      {
        "outline": "The Full Armor of God",
        "verses": [
          "10-20"
        ],
        "references": []
      },
      {
        "outline": "Final Greetings",
        "verses": [
          "21-24"
        ],
        "references": [
          "Philippians 4:21–23",
          "2 Timothy 4:19–22"
        ]
      }
    ]
  }
}