{
  "chapterTopics": {
    "1": [
      {
        "outline": "A Greeting from James",
        "verses": [
          "1"
        ],
        "references": [
          "Jude 1:1–2"
        ]
      },
      {
        "outline": "Rejoicing in Trials",
        "verses": [
          "2-12"
        ],
        "references": [
          "Philippians 1:12–20"
        ]
      },
      {
        "outline": "Good and Perfect Gifts",
        "verses": [
          "13-18"
        ],
        "references": []
      },
      {
        "outline": "Hearing and Doing",
        "verses": [
          "19-27"
        ],
        "references": []
      }
    ],
    "2": [
      {
        "outline": "A Warning against Favoritism",
        "verses": [
          "1-13"
        ],
        "references": []
      },
      {
        "outline": "Faith and Works",
        "verses": [
          "14-26"
        ],
        "references": [
          "Galatians 3:1–9"
        ]
      }
    ],
    "3": [
      {
        "outline": "Taming the Tongue",
        "verses": [
          "1-12"
        ],
        "references": [
          "Psalms 64:1–10"
        ]
      },
      {
        "outline": "The Wisdom from Above",
        "verses": [
          "13-18"
        ],
        "references": []
      }
    ],
    "4": [
      {
        "outline": "A Warning against Pride",
        "verses": [
          "1-6"
        ],
        "references": []
      },
      {
        "outline": "Drawing Near to God",
        "verses": [
          "7-12"
        ],
        "references": []
      },
      {
        "outline": "Do Not Boast about Tomorrow",
        "verses": [
          "13-17"
        ],
        "references": [
          "Proverbs 27:1"
        ]
      }
    ],
    "5": [
      {
        "outline": "A Warning to the Rich",
        "verses": [
          "1-6"
        ],
        "references": [
          "Proverbs 23:1–5",
          "1 Timothy 6:17–19"
        ]
      },
      {
        "outline": "Patience in Suffering",
        "verses": [
          "7-12"
        ],
        "references": [
          "Job 1:1–5"
        ]
      },
      {
        "outline": "The Prayer of Faith",
        "verses": [
          "13-18"
        ],
        "references": []
      },
      {
        "outline": "Restoring a Sinner",
        "verses": [
          "19-20"
        ],
        "references": []
      }
    ]
  }
}